dyca/__init__.py
dyca/src/__init__.py
dyca/src/dyca.py
dyca/src/dyca_internal.py
dyca-1.0.2.dist-info/licenses/LICENSE
dyca-1.0.2.dist-info/METADATA
dyca-1.0.2.dist-info/WHEEL
dyca-1.0.2.dist-info/top_level.txt
dyca-1.0.2.dist-info/RECORD
