Metadata-Version: 2.4
Name: dyca
Version: 1.0.2
Summary: Dynamical Component Analysis - A method to decompose multivariate signals
Home-page: https://github.com/HS-Ansbach-CCS/dyca
Author: Annika Stiehl
Author-email: annika.stiehl@hs-ansbach.de
License: GPL-3.0
Classifier: Intended Audience :: Science/Research
Classifier: License :: OSI Approved :: GNU General Public License v3 (GPLv3)
Classifier: Programming Language :: Python :: 3.10
Classifier: Topic :: Scientific/Engineering :: Information Analysis
Classifier: Topic :: Scientific/Engineering :: Mathematics
Requires-Python: >=3.10
License-File: LICENSE
Requires-Dist: numpy<2.0.0,>=1.18.0
Requires-Dist: matplotlib
Requires-Dist: scipy>=1.13.0
Provides-Extra: dev
Requires-Dist: twine>=4.0.2; extra == "dev"
Dynamic: author
Dynamic: author-email
Dynamic: classifier
Dynamic: description
Dynamic: description-content-type
Dynamic: home-page
Dynamic: license
Dynamic: license-file
Dynamic: provides-extra
Dynamic: requires-dist
Dynamic: requires-python
Dynamic: summary
